diffgram/__init__.py
diffgram/brain/__init__.py
diffgram/brain/brain.py
diffgram/brain/inference.py
diffgram/brain/instance.py
diffgram/brain/train.py
diffgram/convert/__init__.py
diffgram/convert/convert.py
diffgram/core/__init__.py
diffgram/core/core.py
diffgram/core/diffgram_dataset_iterator.py
diffgram/core/directory.py
diffgram/core/directory_samples.py
diffgram/core/sliced_directory.py
diffgram/export/__init__.py
diffgram/export/export.py
diffgram/file/__init__.py
diffgram/file/compound_file.py
diffgram/file/conversational.py
diffgram/file/file.py
diffgram/file/file_3d.py
diffgram/file/file_constructor.py
diffgram/file/test_existing_instances.py
diffgram/file/test_file.py
diffgram/file/view.py
diffgram/job/__init__.py
diffgram/job/guide.py
diffgram/job/job.py
diffgram/label/__init__.py
diffgram/label/label_new.py
diffgram/label/test_label.py
diffgram/member/__init__.py
diffgram/pytorch_diffgram/__init__.py
diffgram/pytorch_diffgram/diffgram_pytorch_dataset.py
diffgram/regular/__init__.py
diffgram/regular/regular.py
diffgram/role/Role.py
diffgram/role/__init__.py
diffgram/schema/__init__.py
diffgram/schema/attribute.py
diffgram/schema/schema.py
diffgram/task/__init__.py
diffgram/task/task.py
diffgram/task/test_task.py
diffgram/tensorflow_diffgram/__init__.py
diffgram/tensorflow_diffgram/diffgram_tensorflow_dataset.py
diffgram/tensorflow_diffgram/pytorch_test.py
diffgram/utils/__init__.py
diffgram/utils/visualization_utils.py
tests/__init__.py
diffgram-0.15.0.dist-info/METADATA
diffgram-0.15.0.dist-info/WHEEL
diffgram-0.15.0.dist-info/top_level.txt
diffgram-0.15.0.dist-info/RECORD
