Metadata-Version: 2.1
Name: diffgram
Version: 0.15.0
Summary: SDK for Diffgram
Home-page: https://github.com/diffgram/python-sdk
Author: Diffgram
Author-email: support@diffgram.com
License: UNKNOWN
Platform: UNKNOWN
Classifier: Programming Language :: Python :: 3
Classifier: License :: OSI Approved :: MIT License
Classifier: Operating System :: OS Independent
Requires-Dist: requests (>=2.20.1)
Provides-Extra: ml
Requires-Dist: imageio (>=2.9.0) ; extra == 'ml'
Requires-Dist: opencv-python (>=4.0.0.21) ; extra == 'ml'
Requires-Dist: pillow (>=6.1.0) ; extra == 'ml'
Requires-Dist: scipy (>=1.1.0) ; extra == 'ml'
Requires-Dist: tensorflow (>=1.12.0) ; extra == 'ml'
Requires-Dist: torch ; extra == 'ml'
